porthouse/__init__.py
porthouse/__main__.py
porthouse/backpipe.py
porthouse/cli.py
porthouse/config.py
porthouse/envelope.py
porthouse/index_page.py
porthouse/ingress.py
porthouse/primary.py
porthouse/register.py
porthouse/rooms.py
porthouse/router.py
porthouse/rules.py
porthouse/run.py
porthouse/tokens.py
porthouse/tool/ac.py
porthouse/tool/ws2.py
porthouse-0.2.2.dist-info/LICENSE
porthouse-0.2.2.dist-info/METADATA
porthouse-0.2.2.dist-info/WHEEL
porthouse-0.2.2.dist-info/entry_points.txt
porthouse-0.2.2.dist-info/top_level.txt
porthouse-0.2.2.dist-info/RECORD
