Metadata-Version: 2.1
Name: porthouse
Version: 0.2.2
Summary: Websocket mesh
Author-email: Porthouse <porthouse@strangemother.com>
License: MIT
Keywords: websockets,mesh
Classifier: Programming Language :: Python :: 3
Classifier: License :: OSI Approved :: MIT License
Classifier: Operating System :: OS Independent
Requires-Python: >=3.8
License-File: LICENSE
